{
  "modelVersion" : "2.3",
  "id" : "TriagemPacienteForm",
  "name" : "TriagemPacienteForm",
  "lastUpdate" : 1687743123497,
  "rows" : [
    [
      {
        "type" : "container",
        "dimension" : {
          "xs" : 12
        },
        "propertyValues" : { },
        "reference" : "e0b0b1b6-bc56-4d1e-b3a2-0494bb6a9773",
        "hasValidationError" : false,
        "id" : "pbContainer",
        "rows" : [
          [
            {
              "type" : "component",
              "dimension" : {
                "md" : 12,
                "sm" : 12,
                "xs" : 12,
                "lg" : 12
              },
              "propertyValues" : {
                "hidden" : {
                  "type" : "constant",
                  "value" : false
                },
                "level" : {
                  "type" : "constant",
                  "value" : "Level 1"
                },
                "cssClasses" : {
                  "type" : "constant",
                  "value" : ""
                },
                "text" : {
                  "type" : "interpolation",
                  "value" : "{{ task.displayName }}"
                },
                "alignment" : {
                  "type" : "constant",
                  "value" : "center"
                },
                "dimension" : {
                  "type" : "constant",
                  "value" : 12
                }
              },
              "reference" : "1274e185-e24c-4a59-b7ed-db54c6c60d03",
              "hasValidationError" : false,
              "id" : "pbTitle",
              "description" : ""
            }
          ],
          [
            {
              "type" : "component",
              "dimension" : {
                "md" : 12,
                "sm" : 12,
                "xs" : 12,
                "lg" : 12
              },
              "propertyValues" : {
                "allowHtml" : {
                  "type" : "constant",
                  "value" : true
                },
                "labelHidden" : {
                  "type" : "constant",
                  "value" : true
                },
                "hidden" : {
                  "type" : "constant",
                  "value" : false
                },
                "cssClasses" : {
                  "type" : "constant",
                  "value" : ""
                },
                "label" : {
                  "type" : "interpolation"
                },
                "text" : {
                  "type" : "interpolation",
                  "value" : "{{ task.displayDescription }}"
                },
                "alignment" : {
                  "type" : "constant",
                  "value" : "left"
                },
                "dimension" : {
                  "type" : "constant",
                  "value" : 12
                }
              },
              "reference" : "68640da7-a2d0-4df6-bef5-b02f77e90aa5",
              "hasValidationError" : false,
              "id" : "pbText",
              "description" : ""
            }
          ]
        ]
      }
    ],
    [
      {
        "type" : "formContainer",
        "dimension" : {
          "xs" : 12
        },
        "propertyValues" : { },
        "reference" : "65e5356b-56f9-4966-81e3-a326c5d75084",
        "hasValidationError" : false,
        "id" : "pbFormContainer",
        "container" : {
          "type" : "container",
          "dimension" : {
            "xs" : 12
          },
          "propertyValues" : { },
          "reference" : "ced27dcc-822c-4ff9-b43d-a0e54807a768",
          "hasValidationError" : false,
          "id" : "pbContainer",
          "rows" : [
            [
              {
                "type" : "component",
                "dimension" : {
                  "md" : 12,
                  "sm" : 12,
                  "xs" : 12,
                  "lg" : 12
                },
                "propertyValues" : {
                  "hidden" : {
                    "type" : "constant",
                    "value" : false
                  },
                  "level" : {
                    "type" : "constant",
                    "value" : "Level 4"
                  },
                  "cssClasses" : {
                    "type" : "constant",
                    "value" : ""
                  },
                  "text" : {
                    "type" : "interpolation",
                    "value" : "Paciente"
                  },
                  "alignment" : {
                    "type" : "constant",
                    "value" : "left"
                  },
                  "dimension" : {
                    "type" : "constant",
                    "value" : 12
                  }
                },
                "reference" : "a522c552-8d64-401e-9e37-55e8b4c201d4",
                "hasValidationError" : false,
                "id" : "pbTitle",
                "description" : ""
              }
            ],
            [
              {
                "type" : "container",
                "dimension" : {
                  "md" : 12,
                  "sm" : 12,
                  "xs" : 12,
                  "lg" : 12
                },
                "propertyValues" : {
                  "repeatedCollection" : {
                    "type" : "variable"
                  },
                  "hidden" : {
                    "type" : "constant",
                    "value" : false
                  },
                  "cssClasses" : {
                    "type" : "constant",
                    "value" : ""
                  },
                  "dimension" : {
                    "type" : "constant",
                    "value" : 12
                  }
                },
                "reference" : "47b73783-36c8-42d2-ad2e-abf15995ea02",
                "hasValidationError" : false,
                "id" : "pbContainer",
                "rows" : [
                  [
                    {
                      "type" : "component",
                      "dimension" : {
                        "md" : 12,
                        "sm" : 12,
                        "xs" : 12,
                        "lg" : 12
                      },
                      "propertyValues" : {
                        "labelHidden" : {
                          "type" : "constant",
                          "value" : false
                        },
                        "hidden" : {
                          "type" : "constant",
                          "value" : false
                        },
                        "labelPosition" : {
                          "type" : "constant",
                          "value" : "top"
                        },
                        "cssClasses" : {
                          "type" : "constant",
                          "value" : ""
                        },
                        "labelWidth" : {
                          "type" : "constant",
                          "value" : 1
                        },
                        "readOnly" : {
                          "type" : "constant",
                          "value" : true
                        },
                        "label" : {
                          "type" : "interpolation",
                          "value" : "Cpf"
                        },
                        "placeholder" : {
                          "type" : "constant"
                        },
                        "type" : {
                          "type" : "constant",
                          "value" : "text"
                        },
                        "dimension" : {
                          "type" : "constant",
                          "value" : 12
                        },
                        "value" : {
                          "type" : "variable",
                          "value" : "paciente.cpf"
                        },
                        "required" : {
                          "type" : "constant",
                          "value" : false
                        },
                        "allowHTML" : {
                          "type" : "constant",
                          "value" : false
                        },
                        "minLength" : {
                          "type" : "constant",
                          "value" : ""
                        },
                        "maxLength" : {
                          "type" : "constant",
                          "value" : ""
                        },
                        "min" : {
                          "type" : "constant"
                        },
                        "max" : {
                          "type" : "constant"
                        },
                        "step" : {
                          "type" : "constant",
                          "value" : 1
                        }
                      },
                      "reference" : "b2486ea7-a655-4abf-9651-975d00d5321a",
                      "hasValidationError" : false,
                      "id" : "pbInput",
                      "description" : ""
                    }
                  ],
                  [
                    {
                      "type" : "component",
                      "dimension" : {
                        "md" : 12,
                        "sm" : 12,
                        "xs" : 12,
                        "lg" : 12
                      },
                      "propertyValues" : {
                        "labelHidden" : {
                          "type" : "constant",
                          "value" : false
                        },
                        "hidden" : {
                          "type" : "constant",
                          "value" : false
                        },
                        "labelPosition" : {
                          "type" : "constant",
                          "value" : "top"
                        },
                        "cssClasses" : {
                          "type" : "constant",
                          "value" : ""
                        },
                        "labelWidth" : {
                          "type" : "constant",
                          "value" : 1
                        },
                        "readOnly" : {
                          "type" : "constant",
                          "value" : true
                        },
                        "label" : {
                          "type" : "interpolation",
                          "value" : "Nome"
                        },
                        "placeholder" : {
                          "type" : "constant"
                        },
                        "type" : {
                          "type" : "constant",
                          "value" : "text"
                        },
                        "dimension" : {
                          "type" : "constant",
                          "value" : 12
                        },
                        "value" : {
                          "type" : "variable",
                          "value" : "paciente.nome"
                        },
                        "required" : {
                          "type" : "constant",
                          "value" : false
                        },
                        "allowHTML" : {
                          "type" : "constant",
                          "value" : false
                        },
                        "minLength" : {
                          "type" : "constant",
                          "value" : ""
                        },
                        "maxLength" : {
                          "type" : "constant",
                          "value" : ""
                        },
                        "min" : {
                          "type" : "constant"
                        },
                        "max" : {
                          "type" : "constant"
                        },
                        "step" : {
                          "type" : "constant",
                          "value" : 1
                        }
                      },
                      "reference" : "9290bf62-ab84-48e3-9e3e-5a846702f693",
                      "hasValidationError" : false,
                      "id" : "pbInput",
                      "description" : ""
                    }
                  ],
                  [
                    {
                      "type" : "component",
                      "dimension" : {
                        "xs" : 12,
                        "sm" : 12,
                        "md" : 4,
                        "lg" : 4
                      },
                      "propertyValues" : {
                        "cssClasses" : {
                          "type" : "constant",
                          "value" : ""
                        },
                        "hidden" : {
                          "type" : "constant",
                          "value" : false
                        },
                        "disabled" : {
                          "type" : "constant",
                          "value" : false
                        },
                        "allowHTML" : {
                          "type" : "constant",
                          "value" : false
                        },
                        "inline" : {
                          "type" : "constant",
                          "value" : true
                        },
                        "labelHidden" : {
                          "type" : "constant",
                          "value" : false
                        },
                        "label" : {
                          "type" : "interpolation",
                          "value" : "Estomatologia"
                        },
                        "labelPosition" : {
                          "type" : "constant",
                          "value" : "top"
                        },
                        "labelWidth" : {
                          "type" : "constant",
                          "value" : 4
                        },
                        "availableValues" : {
                          "type" : "constant",
                          "value" : [
                            "esAc",
                            "esBIO"
                          ]
                        },
                        "displayedKey" : {
                          "type" : "constant"
                        },
                        "returnedKey" : {
                          "type" : "constant"
                        },
                        "selectedValues" : {
                          "type" : "variable",
                          "value" : "paciente.estomatologia"
                        }
                      },
                      "reference" : "8b9a0b90-9c35-4c1e-9ef9-0808b15f210e",
                      "hasValidationError" : false,
                      "id" : "pbChecklist"
                    }
                  ],
                  [
                    {
                      "type" : "component",
                      "dimension" : {
                        "xs" : 12,
                        "sm" : 12,
                        "md" : 6,
                        "lg" : 6
                      },
                      "propertyValues" : {
                        "cssClasses" : {
                          "type" : "constant",
                          "value" : ""
                        },
                        "hidden" : {
                          "type" : "constant",
                          "value" : false
                        },
                        "disabled" : {
                          "type" : "constant",
                          "value" : false
                        },
                        "allowHTML" : {
                          "type" : "constant",
                          "value" : false
                        },
                        "inline" : {
                          "type" : "constant",
                          "value" : true
                        },
                        "labelHidden" : {
                          "type" : "constant",
                          "value" : false
                        },
                        "label" : {
                          "type" : "interpolation",
                          "value" : "Dentistica"
                        },
                        "labelPosition" : {
                          "type" : "constant",
                          "value" : "top"
                        },
                        "labelWidth" : {
                          "type" : "constant",
                          "value" : 4
                        },
                        "availableValues" : {
                          "type" : "constant",
                          "value" : [
                            "De1",
                            "De2"
                          ]
                        },
                        "displayedKey" : {
                          "type" : "constant"
                        },
                        "returnedKey" : {
                          "type" : "constant"
                        },
                        "selectedValues" : {
                          "type" : "variable",
                          "value" : "paciente.dentistica"
                        }
                      },
                      "reference" : "2adac705-dacc-481a-9d51-28db67ddbc30",
                      "hasValidationError" : false,
                      "id" : "pbChecklist"
                    }
                  ],
                  [
                    {
                      "type" : "component",
                      "dimension" : {
                        "xs" : 12,
                        "sm" : 12,
                        "md" : 6,
                        "lg" : 6
                      },
                      "propertyValues" : {
                        "cssClasses" : {
                          "type" : "constant",
                          "value" : ""
                        },
                        "hidden" : {
                          "type" : "constant",
                          "value" : false
                        },
                        "disabled" : {
                          "type" : "constant",
                          "value" : false
                        },
                        "allowHTML" : {
                          "type" : "constant",
                          "value" : false
                        },
                        "inline" : {
                          "type" : "constant",
                          "value" : true
                        },
                        "labelHidden" : {
                          "type" : "constant",
                          "value" : false
                        },
                        "label" : {
                          "type" : "interpolation",
                          "value" : "Cirurgia"
                        },
                        "labelPosition" : {
                          "type" : "constant",
                          "value" : "top"
                        },
                        "labelWidth" : {
                          "type" : "constant",
                          "value" : 4
                        },
                        "availableValues" : {
                          "type" : "constant",
                          "value" : [
                            "Ci1",
                            "Ci2"
                          ]
                        },
                        "displayedKey" : {
                          "type" : "constant"
                        },
                        "returnedKey" : {
                          "type" : "constant"
                        },
                        "selectedValues" : {
                          "type" : "variable",
                          "value" : "paciente.cirurgia"
                        }
                      },
                      "reference" : "1a6542fc-9df6-4f29-917e-29defcb96fb5",
                      "hasValidationError" : false,
                      "id" : "pbChecklist"
                    }
                  ],
                  [
                    {
                      "type" : "component",
                      "dimension" : {
                        "xs" : 12,
                        "sm" : 12,
                        "md" : 6,
                        "lg" : 6
                      },
                      "propertyValues" : {
                        "cssClasses" : {
                          "type" : "constant",
                          "value" : ""
                        },
                        "hidden" : {
                          "type" : "constant",
                          "value" : false
                        },
                        "disabled" : {
                          "type" : "constant",
                          "value" : false
                        },
                        "allowHTML" : {
                          "type" : "constant",
                          "value" : false
                        },
                        "inline" : {
                          "type" : "constant",
                          "value" : true
                        },
                        "labelHidden" : {
                          "type" : "constant",
                          "value" : false
                        },
                        "label" : {
                          "type" : "interpolation",
                          "value" : "Periodontia"
                        },
                        "labelPosition" : {
                          "type" : "constant",
                          "value" : "top"
                        },
                        "labelWidth" : {
                          "type" : "constant",
                          "value" : 4
                        },
                        "availableValues" : {
                          "type" : "constant",
                          "value" : [
                            "pe0",
                            "peNt",
                            "peCi",
                            "peTr"
                          ]
                        },
                        "displayedKey" : {
                          "type" : "constant"
                        },
                        "returnedKey" : {
                          "type" : "constant"
                        },
                        "selectedValues" : {
                          "type" : "variable",
                          "value" : "paciente.periodontia"
                        }
                      },
                      "reference" : "4b34ab00-ed6a-4780-bd27-b5e7cb16583d",
                      "hasValidationError" : false,
                      "id" : "pbChecklist"
                    }
                  ],
                  [
                    {
                      "type" : "component",
                      "dimension" : {
                        "xs" : 12,
                        "sm" : 12,
                        "md" : 6,
                        "lg" : 6
                      },
                      "propertyValues" : {
                        "cssClasses" : {
                          "type" : "constant",
                          "value" : ""
                        },
                        "hidden" : {
                          "type" : "constant",
                          "value" : false
                        },
                        "disabled" : {
                          "type" : "constant",
                          "value" : false
                        },
                        "allowHTML" : {
                          "type" : "constant",
                          "value" : false
                        },
                        "inline" : {
                          "type" : "constant",
                          "value" : true
                        },
                        "labelHidden" : {
                          "type" : "constant",
                          "value" : false
                        },
                        "label" : {
                          "type" : "interpolation",
                          "value" : "Endodontia"
                        },
                        "labelPosition" : {
                          "type" : "constant",
                          "value" : "top"
                        },
                        "labelWidth" : {
                          "type" : "constant",
                          "value" : 4
                        },
                        "availableValues" : {
                          "type" : "constant",
                          "value" : [
                            "en1",
                            "en2"
                          ]
                        },
                        "displayedKey" : {
                          "type" : "constant"
                        },
                        "returnedKey" : {
                          "type" : "constant"
                        },
                        "selectedValues" : {
                          "type" : "variable",
                          "value" : "paciente.endodontia"
                        }
                      },
                      "reference" : "e93ba24e-2e67-4ac5-978c-7f593146e1bc",
                      "hasValidationError" : false,
                      "id" : "pbChecklist"
                    }
                  ],
                  [
                    {
                      "type" : "component",
                      "dimension" : {
                        "xs" : 12,
                        "sm" : 12,
                        "md" : 6,
                        "lg" : 6
                      },
                      "propertyValues" : {
                        "cssClasses" : {
                          "type" : "constant",
                          "value" : ""
                        },
                        "hidden" : {
                          "type" : "constant",
                          "value" : false
                        },
                        "disabled" : {
                          "type" : "constant",
                          "value" : false
                        },
                        "allowHTML" : {
                          "type" : "constant",
                          "value" : false
                        },
                        "inline" : {
                          "type" : "constant",
                          "value" : true
                        },
                        "labelHidden" : {
                          "type" : "constant",
                          "value" : false
                        },
                        "label" : {
                          "type" : "interpolation",
                          "value" : "Protese"
                        },
                        "labelPosition" : {
                          "type" : "constant",
                          "value" : "top"
                        },
                        "labelWidth" : {
                          "type" : "constant",
                          "value" : 4
                        },
                        "availableValues" : {
                          "type" : "constant",
                          "value" : [
                            "pt",
                            "ppr",
                            "fixa",
                            "pti",
                            "placa"
                          ]
                        },
                        "displayedKey" : {
                          "type" : "constant"
                        },
                        "returnedKey" : {
                          "type" : "constant"
                        },
                        "selectedValues" : {
                          "type" : "variable",
                          "value" : "paciente.protese"
                        }
                      },
                      "reference" : "63280e61-1f78-40f2-9e58-9ea1963dd0bf",
                      "hasValidationError" : false,
                      "id" : "pbChecklist"
                    }
                  ]
                ]
              }
            ],
            [
              {
                "type" : "component",
                "dimension" : {
                  "md" : 12,
                  "sm" : 12,
                  "xs" : 12,
                  "lg" : 12
                },
                "propertyValues" : {
                  "removeItem" : {
                    "type" : "variable"
                  },
                  "hidden" : {
                    "type" : "constant",
                    "value" : false
                  },
                  "cssClasses" : {
                    "type" : "constant",
                    "value" : ""
                  },
                  "buttonStyle" : {
                    "type" : "constant",
                    "value" : "primary"
                  },
                  "label" : {
                    "type" : "interpolation",
                    "value" : "Concluir triagem"
                  },
                  "dataToSend" : {
                    "type" : "expression",
                    "value" : "formOutput"
                  },
                  "dataFromError" : {
                    "type" : "variable",
                    "value" : "formOutput._submitError"
                  },
                  "labelHidden" : {
                    "type" : "constant",
                    "value" : false
                  },
                  "collectionPosition" : {
                    "type" : "constant"
                  },
                  "targetUrlOnSuccess" : {
                    "type" : "interpolation",
                    "value" : "/bonita"
                  },
                  "action" : {
                    "type" : "constant",
                    "value" : "Submit task"
                  },
                  "collectionToModify" : {
                    "type" : "variable"
                  },
                  "valueToAdd" : {
                    "type" : "expression"
                  },
                  "disabled" : {
                    "type" : "expression",
                    "value" : "$form.$invalid"
                  },
                  "alignment" : {
                    "type" : "constant",
                    "value" : "center"
                  },
                  "dimension" : {
                    "type" : "constant",
                    "value" : 12
                  },
                  "allowHTML" : {
                    "type" : "constant",
                    "value" : false
                  },
                  "assign" : {
                    "type" : "constant",
                    "value" : false
                  },
                  "url" : {
                    "type" : "interpolation"
                  },
                  "responseStatusCode" : {
                    "type" : "variable"
                  },
                  "dataFromSuccess" : {
                    "type" : "variable"
                  },
                  "closeOnSuccess" : {
                    "type" : "constant",
                    "value" : false
                  },
                  "modalId" : {
                    "type" : "constant",
                    "value" : ""
                  }
                },
                "reference" : "07890a1c-5b3b-4b99-bdf4-3721eb8c44db",
                "hasValidationError" : false,
                "id" : "pbButton",
                "description" : ""
              }
            ],
            [
              {
                "type" : "component",
                "dimension" : {
                  "md" : 12,
                  "sm" : 12,
                  "xs" : 12,
                  "lg" : 12
                },
                "propertyValues" : {
                  "allowHTML" : {
                    "type" : "constant",
                    "value" : true
                  },
                  "allowHtml" : {
                    "type" : "constant",
                    "value" : true
                  },
                  "labelHidden" : {
                    "type" : "constant",
                    "value" : true
                  },
                  "hidden" : {
                    "type" : "expression",
                    "value" : "!formOutput._submitError.message"
                  },
                  "cssClasses" : {
                    "type" : "constant",
                    "value" : "alert alert-danger col-lg-6 col-lg-offset-3"
                  },
                  "label" : {
                    "type" : "interpolation"
                  },
                  "text" : {
                    "type" : "interpolation",
                    "value" : "<strong>Debug message</strong>\n<br/>\n{{formOutput._submitError.message}}\n{{submit_errors_list}}"
                  },
                  "alignment" : {
                    "type" : "constant",
                    "value" : "left"
                  },
                  "dimension" : {
                    "type" : "constant",
                    "value" : 12
                  }
                },
                "reference" : "83372b4c-1c92-4f00-98a0-58341733bf0d",
                "hasValidationError" : false,
                "id" : "pbText",
                "description" : ""
              }
            ]
          ]
        }
      }
    ]
  ],
  "assets" : [
    {
      "id" : "7ac630da-6b72-41ba-a2d3-1fce5d61cda3",
      "name" : "localization.json",
      "type" : "json",
      "order" : 0,
      "external" : false
    },
    {
      "id" : "39b5a78d-7a33-44a4-a385-95463b9a9f12",
      "name" : "style.css",
      "type" : "css",
      "order" : 0,
      "external" : false
    }
  ],
  "inactiveAssets" : [ ],
  "variables" : {
    "task" : {
      "type" : "url",
      "value" : [
        "../API/bpm/userTask/{{taskId}}"
      ],
      "exposed" : false
    },
    "submit_errors_list" : {
      "type" : "expression",
      "value" : [
        "if($data.formOutput && $data.formOutput._submitError && $data.formOutput._submitError.explanations){",
        "\tconst liElements = $data.formOutput._submitError.explanations",
        "\t\t.filter(cause => cause !== null)",
        "\t\t.map(cause => \"<li>\" + cause + \"</li>\")",
        "\t\t.join('');",
        "\tif(liElements){",
        "\t\treturn \"<ul>\" + liElements + \"</ul>\";",
        "\t}",
        "}"
      ],
      "exposed" : false
    },
    "paciente" : {
      "type" : "url",
      "value" : [
        "../{{context.paciente_ref.link}}"
      ],
      "exposed" : false
    },
    "formOutput" : {
      "type" : "expression",
      "value" : [
        "if( $data.paciente ){",
        "\treturn {",
        "\t\t//map paciente variable to expected task contract input",
        "\t\tpacienteInput: {",
        "\t\t\tcpf: $data.paciente.cpf !== undefined ? $data.paciente.cpf : null,",
        "\t\t\tnome: $data.paciente.nome !== undefined ? $data.paciente.nome : null,",
        "\t\t\tsituacaoAtendimento: $data.paciente.situacaoAtendimento !== undefined ? \"Triado\" : null,",
        "\t\t\testomatologia: $data.paciente.estomatologia !== undefined ? $data.estomatologiaVarForm : null,",
        "\t\t\tdentistica: $data.paciente.dentistica !== undefined ? $data.dentisticaVarForm : null,",
        "\t\t\tcirurgia: $data.paciente.cirurgia !== undefined ? $data.cirurgiaVarForm : null,",
        "\t\t\tperiodontia: $data.paciente.periodontia !== undefined ? $data.periodontiaVarForm : null,",
        "\t\t\tendodontia: $data.paciente.endodontia !== undefined ? $data.endodontiaVarForm : null,",
        "\t\t\tprotese: $data.paciente.protese !== undefined ? $data.proteseVarForm : null,",
        "\t\t\tprocedimentosRealizados: $data.paciente.procedimentosRealizados !== undefined ? $data.paciente.procedimentosRealizados : null",
        "\t\t}",
        "\t}",
        "}"
      ],
      "exposed" : false
    },
    "context" : {
      "type" : "url",
      "value" : [
        "../API/bpm/userTask/{{taskId}}/context"
      ],
      "exposed" : false
    },
    "taskId" : {
      "type" : "urlparameter",
      "value" : [
        "id"
      ],
      "exposed" : false
    },
    "estomatologiaVarForm" : {
      "type" : "expression",
      "value" : [
        "var resposta = \"\";",
        "for (var index in $data.paciente.estomatologia){",
        "    if (index == 0){",
        "        resposta += $data.paciente.estomatologia[index];",
        "    }else{",
        "        resposta += \" \" + $data.paciente.estomatologia[index];",
        "    }",
        "}",
        "return resposta"
      ],
      "exposed" : false
    },
    "dentisticaVarForm" : {
      "type" : "expression",
      "value" : [
        "var resposta = \"\";",
        "for (var index in $data.paciente.dentistica){",
        "    if (index == 0){",
        "        resposta += $data.paciente.dentistica[index];",
        "    }else{",
        "        resposta += \" \" + $data.paciente.dentistica[index];",
        "    }",
        "}",
        "return resposta"
      ],
      "exposed" : false
    },
    "cirurgiaVarForm" : {
      "type" : "expression",
      "value" : [
        "var resposta = \"\";",
        "for (var index in $data.paciente.cirurgia){",
        "    if (index == 0){",
        "        resposta += $data.paciente.cirurgia[index];",
        "    }else{",
        "        resposta += \" \" + $data.paciente.cirurgia[index];",
        "    }",
        "}",
        "return resposta"
      ],
      "exposed" : false
    },
    "periodontiaVarForm" : {
      "type" : "expression",
      "value" : [
        "var resposta = \"\";",
        "for (var index in $data.paciente.periodontia){",
        "    if (index == 0){",
        "        resposta += $data.paciente.periodontia[index];",
        "    }else{",
        "        resposta += \" \" + $data.paciente.periodontia[index];",
        "    }",
        "}",
        "return resposta"
      ],
      "exposed" : false
    },
    "endodontiaVarForm" : {
      "type" : "expression",
      "value" : [
        "var resposta = \"\";",
        "for (var index in $data.paciente.endodontia){",
        "    if (index == 0){",
        "        resposta += $data.paciente.endodontia[index];",
        "    }else{",
        "        resposta += \" \" + $data.paciente.endodontia[index];",
        "    }",
        "}",
        "return resposta"
      ],
      "exposed" : false
    },
    "proteseVarForm" : {
      "type" : "expression",
      "value" : [
        "var resposta = \"\";",
        "for (var index in $data.paciente.protese){",
        "    if (index == 0){",
        "        resposta += $data.paciente.protese[index];",
        "    }else{",
        "        resposta += \" \" + $data.paciente.protese[index];",
        "    }",
        "}",
        "return resposta"
      ],
      "exposed" : false
    }
  },
  "hasValidationError" : false,
  "uuid" : "7e3076b4-a5ac-4a3d-82c5-7e4f9e96b876",
  "type" : "form",
  "description" : "Page generated with Bonita UI designer"
}